nowcasting_dataset/__init__.py
nowcasting_dataset/consts.py
nowcasting_dataset/geospatial.py
nowcasting_dataset/square.py
nowcasting_dataset/time.py
nowcasting_dataset/utils.py
nowcasting_dataset/config/__init__.py
nowcasting_dataset/config/gcp.yaml
nowcasting_dataset/config/load.py
nowcasting_dataset/config/model.py
nowcasting_dataset/config/on_premises.yaml
nowcasting_dataset/config/save.py
nowcasting_dataset/data_sources/__init__.py
nowcasting_dataset/data_sources/data_source.py
nowcasting_dataset/data_sources/datasource_output.py
nowcasting_dataset/data_sources/map.py
nowcasting_dataset/data_sources/fake/__init__.py
nowcasting_dataset/data_sources/fake/batch.py
nowcasting_dataset/data_sources/fake/coordinates.py
nowcasting_dataset/data_sources/fake/utils.py
nowcasting_dataset/data_sources/gsp/__init__.py
nowcasting_dataset/data_sources/gsp/eso.py
nowcasting_dataset/data_sources/gsp/gsp_data_source.py
nowcasting_dataset/data_sources/gsp/gsp_model.py
nowcasting_dataset/data_sources/gsp/live.py
nowcasting_dataset/data_sources/gsp/pvlive.py
nowcasting_dataset/data_sources/metadata/__init__.py
nowcasting_dataset/data_sources/metadata/metadata_model.py
nowcasting_dataset/data_sources/nwp/__init__.py
nowcasting_dataset/data_sources/nwp/nwp_data_source.py
nowcasting_dataset/data_sources/nwp/nwp_model.py
nowcasting_dataset/data_sources/optical_flow/__init__.py
nowcasting_dataset/data_sources/optical_flow/format_images.py
nowcasting_dataset/data_sources/optical_flow/optical_flow_data_source.py
nowcasting_dataset/data_sources/optical_flow/optical_flow_model.py
nowcasting_dataset/data_sources/pv/__init__.py
nowcasting_dataset/data_sources/pv/live.py
nowcasting_dataset/data_sources/pv/pv_data_source.py
nowcasting_dataset/data_sources/pv/pv_model.py
nowcasting_dataset/data_sources/pv/utils.py
nowcasting_dataset/data_sources/satellite/__init__.py
nowcasting_dataset/data_sources/satellite/satellite_data_source.py
nowcasting_dataset/data_sources/satellite/satellite_model.py
nowcasting_dataset-3.8.2.dist-info/LICENSE
nowcasting_dataset-3.8.2.dist-info/METADATA
nowcasting_dataset-3.8.2.dist-info/WHEEL
nowcasting_dataset-3.8.2.dist-info/top_level.txt
nowcasting_dataset-3.8.2.dist-info/RECORD
