Metadata-Version: 2.1
Name: nowcasting-dataset
Version: 3.8.2
Summary: Nowcasting Dataset
Author: Jack Kelly, Peter Dudfield, Jacob Bieker
Author-email: info@openclimatefix.org
License: MIT
License-File: LICENSE
Requires-Dist: rioxarray
Requires-Dist: numpy
Requires-Dist: pandas
Requires-Dist: geopandas
Requires-Dist: zarr
Requires-Dist: xarray
Requires-Dist: h5netcdf
Requires-Dist: gcsfs
Requires-Dist: dask
Requires-Dist: pvlib
Requires-Dist: pyproj
Requires-Dist: pytest
Requires-Dist: coverage <6.3
Requires-Dist: pytest-cov
Requires-Dist: ocf-blosc2
Requires-Dist: jedi
Requires-Dist: mypy
Requires-Dist: pydantic
Requires-Dist: tqdm
Requires-Dist: fsspec
Requires-Dist: pathy
Requires-Dist: opencv-contrib-python-headless
Requires-Dist: gitpython
Requires-Dist: pyresample
Requires-Dist: nowcasting-datamodel >=1.4.4
Requires-Dist: scipy
Requires-Dist: pyaml-env
Requires-Dist: fsspec ==2023.1.0
Provides-Extra: full
Requires-Dist: black ; extra == 'full'
Requires-Dist: plotly ; extra == 'full'
Requires-Dist: gcsfs ; extra == 'full'
Requires-Dist: matplotlib ; extra == 'full'
Requires-Dist: ipykernel ; extra == 'full'
Requires-Dist: pre-commit ; extra == 'full'
